setup.py
wechatntf/__init__.py
wechatntf/test.py
wechatntf/wechat_config.py
wechatntf/wechatntf.py
wechatntf.egg-info/PKG-INFO
wechatntf.egg-info/SOURCES.txt
wechatntf.egg-info/dependency_links.txt
wechatntf.egg-info/requires.txt
wechatntf.egg-info/top_level.txt
wechatntf/config/__init__.py