Metadata-Version: 1.0
Name: wechatntf
Version: 1.11.6
Summary: An wechat notification app, using api from WxPusher, only for personal 
Home-page: https://www.mengma021.com
Author: xinghuaizhen
Author-email: xinghuaizhen1989@gmail.com
License: GNU General Public License v3.0
Platform: UNKNOWN
